[
  {
    "HUMAN_READABLE_NAME": "Blush Pink"
  },
  {
    "HUMAN_READABLE_NAME": "Medium Blue"
  },
  {
    "HUMAN_READABLE_NAME": "Premium Hazy Blue Windowpane"
  },
  {
    "HUMAN_READABLE_NAME": "Premium Hazy Blue Windowpane"
  },
  {
    "HUMAN_READABLE_NAME": "Premium Hazy Blue Windowpane"
  },
  {
    "HUMAN_READABLE_NAME": "Blush Pink"
  },
  {
    "HUMAN_READABLE_NAME": "Black"
  },
  {
    "HUMAN_READABLE_NAME": "Performance Tahitian Tide"
  },
  {
    "HUMAN_READABLE_NAME": "Black"
  },
  {
    "HUMAN_READABLE_NAME": "Salmon Pink"
  },
  {
    "HUMAN_READABLE_NAME": "Medium Blue"
  },
  {
    "HUMAN_READABLE_NAME": "Seafoam Performance Blend"
  },
  {
    "HUMAN_READABLE_NAME": "Seafoam Performance Blend"
  },
  {
    "HUMAN_READABLE_NAME": "Dark Khaki 5-Pocket"
  },
  {
    "HUMAN_READABLE_NAME": "Dark Khaki Chino"
  },
  {
    "HUMAN_READABLE_NAME": "Dark Khaki"
  },
  {
    "HUMAN_READABLE_NAME": "Wrinkle Free Diamond Checks"
  },
  {
    "HUMAN_READABLE_NAME": "Wrinkle Free Diamond Checks"
  },
  {
    "HUMAN_READABLE_NAME": "Mountain View"
  },
  {
    "HUMAN_READABLE_NAME": "Mountain View"
  },
  {
    "HUMAN_READABLE_NAME": "Mountain View"
  },
  {
    "HUMAN_READABLE_NAME": "Mountain View"
  },
  {
    "HUMAN_READABLE_NAME": "Mountain View"
  },
  {
    "HUMAN_READABLE_NAME": "Mountain View"
  },
  {
    "HUMAN_READABLE_NAME": "Mountain View"
  },
  {
    "HUMAN_READABLE_NAME": "Mountain View"
  }
]